vsl_json.py
vsl_json-0.0.4.dist-info/licenses/LICENSE
vsl_json-0.0.4.dist-info/METADATA
vsl_json-0.0.4.dist-info/WHEEL
vsl_json-0.0.4.dist-info/top_level.txt
vsl_json-0.0.4.dist-info/RECORD
